lime_ndt/__init__.py
lime_ndt/discretize.py
lime_ndt/explanation.py
lime_ndt/lime_base.py
lime_ndt/lime_tabular.py
lime_ndt/ndt/__init__.py
lime_ndt/ndt/model/Neural_Decision_Tree.py
lime_ndt/ndt/model/__init__.py
lime_ndt/ndt/utils/__init__.py
lime_ndt/ndt/utils/common_functions.py
lime_ndt/ndt/utils/comparison_functions.py
lime_ndt/tests/__init__.py
lime_ndt/tests/test_discretize.py
lime_ndt/tests/test_generic_utils.py
lime_ndt/tests/test_lime_tabular.py
lime_ndt/utils/__init__.py
lime_ndt/utils/generic_utils.py
lime_ndt/utils/ndt_sklearn_wrapper.py
lime_ndt/wrappers/__init__.py
lime_ndt/wrappers/scikit_image.py
lime_ndt-0.1.5.dist-info/licenses/LICENSE
lime_ndt-0.1.5.dist-info/METADATA
lime_ndt-0.1.5.dist-info/WHEEL
lime_ndt-0.1.5.dist-info/top_level.txt
lime_ndt-0.1.5.dist-info/RECORD
