Metadata-Version: 2.4
Name: lime_ndt
Version: 0.1.5
Summary: Enhancing LIME through Neural Decision Trees
Home-page: https://github.com/aymen20002005/lime_ndt/tree/main
Author: Mohamed Aymen BOUYAHIA
Author-email: mohamed-aymen.bouyahia@ensta-paris.fr
Classifier: Programming Language :: Python :: 3
Classifier: License :: OSI Approved :: MIT License
Classifier: Operating System :: OS Independent
Requires-Python: >=3.7
License-File: LICENSE
Requires-Dist: numpy
Requires-Dist: pandas
Requires-Dist: scikit-learn
Requires-Dist: matplotlib
Requires-Dist: keras
Requires-Dist: tensorflow
Dynamic: author
Dynamic: author-email
Dynamic: classifier
Dynamic: description
Dynamic: description-content-type
Dynamic: home-page
Dynamic: license-file
Dynamic: requires-dist
Dynamic: requires-python
Dynamic: summary
